qlogin/__init__.py
qlogin/main_module.py
qlogin/qlogin.py
qlogin-0.1.2.dist-info/LICENSE
qlogin-0.1.2.dist-info/METADATA
qlogin-0.1.2.dist-info/WHEEL
qlogin-0.1.2.dist-info/top_level.txt
qlogin-0.1.2.dist-info/RECORD
