Metadata-Version: 2.1
Name: qlogin
Version: 0.1.2
Summary: QQ空间登录组件
Home-page: https://github.com/LibraHp/Qlogin
Author: LibraHp
Author-email: 1941163264@qq.com
License: UNKNOWN
Platform: UNKNOWN
Classifier: Programming Language :: Python :: 3
Classifier: License :: OSI Approved :: MIT License
Classifier: Operating System :: OS Independent
Requires-Python: >=3.6
License-File: LICENSE
Requires-Dist: requests
